{
	"info": {
		"_postman_id": "82cf1d71-8185-4f7b-b690-5e8bd9fefb33",
		"name": "Mock Facebook",
		"schema": "https://schema.getpostman.com/json/collection/v2.1.0/collection.json",
		"_exporter_id": "23525004"
	},
	"item": [
		{
			"name": "users",
			"protocolProfileBehavior": {
				"disableBodyPruning": true
			},
			"request": {
				"method": "GET",
				"header": [],
				"body": {
					"mode": "raw",
					"raw": ""
				},
				"url": {
					"raw": "{{url}}/users",
					"host": [
						"{{url}}"
					],
					"path": [
						"users"
					]
				}
			},
			"response": [
				{
					"name": "Default",
					"originalRequest": {
						"method": "GET",
						"header": [],
						"body": {
							"mode": "raw",
							"raw": ""
						},
						"url": {
							"raw": "https://01b125e6-540b-4f25-986c-5b75dd58cd4e.mock.pstmn.io/users",
							"protocol": "https",
							"host": [
								"01b125e6-540b-4f25-986c-5b75dd58cd4e",
								"mock",
								"pstmn",
								"io"
							],
							"path": [
								"users"
							]
						}
					},
					"code": 200,
					"_postman_previewlanguage": "json",
					"header": [
						{
							"key": "Content-Type",
							"value": "application/json",
							"name": "Content-Type",
							"description": "",
							"type": "text"
						}
					],
					"cookie": [],
					"body": "{\r\n    \"user\": \"Marysia\"\r\n}"
				}
			]
		},
		{
			"name": "user/1",
			"request": {
				"method": "DELETE",
				"header": [],
				"body": {
					"mode": "raw",
					"raw": ""
				},
				"url": {
					"raw": "{{url}}/user/1",
					"host": [
						"{{url}}"
					],
					"path": [
						"user",
						"1"
					]
				}
			},
			"response": [
				{
					"name": "Default",
					"originalRequest": {
						"method": "DELETE",
						"header": [],
						"body": {
							"mode": "raw",
							"raw": ""
						},
						"url": {
							"raw": "{{url}}/user/1",
							"host": [
								"{{url}}"
							],
							"path": [
								"user",
								"1"
							]
						}
					},
					"code": 204,
					"_postman_previewlanguage": null,
					"header": null,
					"cookie": [],
					"body": ""
				}
			]
		}
	],
	"variable": [
		{
			"key": "url",
			"value": "https://01b125e6-540b-4f25-986c-5b75dd58cd4e.mock.pstmn.io"
		}
	]
}